trading_state/__init__.py
trading_state/allocate.py
trading_state/balance.py
trading_state/common.py
trading_state/config.py
trading_state/enums.py
trading_state/exceptions.py
trading_state/filters.py
trading_state/order.py
trading_state/order_ticket.py
trading_state/pnl.py
trading_state/position.py
trading_state/py.typed
trading_state/state.py
trading_state/symbol.py
trading_state/target.py
trading_state/binance/__init__.py
trading_state/binance/balance.py
trading_state/binance/exchange_info.py
trading_state/binance/order.py
trading_state-0.0.2.dist-info/licenses/LICENSE
trading_state-0.0.2.dist-info/METADATA
trading_state-0.0.2.dist-info/WHEEL
trading_state-0.0.2.dist-info/top_level.txt
trading_state-0.0.2.dist-info/RECORD
