Metadata-Version: 2.4
Name: trading-state
Version: 0.0.2
Summary: A lightweight Python engine for simulating trading account balances, order states, and exchange-style constraints.
Author-email: Kael Zhang <i+pypi@kael.me>
Project-URL: Homepage, https://github.com/kaelzhang/python-trading-state
Keywords: trading-state
Classifier: Topic :: Software Development :: Libraries :: Python Modules
Classifier: Programming Language :: Python :: 3.12
Classifier: Programming Language :: Python :: Implementation :: PyPy
Requires-Python: >=3.12
License-File: LICENSE
Provides-Extra: dev
Requires-Dist: coverage; extra == "dev"
Requires-Dist: ruff; extra == "dev"
Requires-Dist: pytest; extra == "dev"
Requires-Dist: pytest-asyncio; extra == "dev"
Requires-Dist: pytest-cov; extra == "dev"
Requires-Dist: twine; extra == "dev"
Requires-Dist: mypy; extra == "dev"
Requires-Dist: build; extra == "dev"
Dynamic: license-file
